gumerov_expansion_coefficients/__init__.py
gumerov_expansion_coefficients/__main__.py
gumerov_expansion_coefficients/_elementary_solutions.py
gumerov_expansion_coefficients/_main.py
gumerov_expansion_coefficients/cli.py
gumerov_expansion_coefficients/py.typed
gumerov_expansion_coefficients-1.2.1.dist-info/licenses/LICENSE
gumerov_expansion_coefficients-1.2.1.dist-info/METADATA
gumerov_expansion_coefficients-1.2.1.dist-info/WHEEL
gumerov_expansion_coefficients-1.2.1.dist-info/entry_points.txt
gumerov_expansion_coefficients-1.2.1.dist-info/top_level.txt
gumerov_expansion_coefficients-1.2.1.dist-info/RECORD
