Metadata-Version: 2.4
Name: gumerov-expansion-coefficients
Version: 1.2.1
Summary: Multiple translation and rotation coefficients for the 3D Helmholtz Equation
Author-email: 34j <34j.95a2p@simplelogin.com>
License: MIT
Project-URL: Bug Tracker, https://github.com/34j/gumerov-expansion-coefficients/issues
Project-URL: Changelog, https://github.com/34j/gumerov-expansion-coefficients/blob/main/CHANGELOG.md
Project-URL: documentation, https://gumerov-expansion-coefficients.readthedocs.io
Project-URL: repository, https://github.com/34j/gumerov-expansion-coefficients
Classifier: Development Status :: 2 - Pre-Alpha
Classifier: Intended Audience :: Developers
Classifier: Natural Language :: English
Classifier: Operating System :: OS Independent
Classifier: Programming Language :: Python :: 3.9
Classifier: Programming Language :: Python :: 3.10
Classifier: Programming Language :: Python :: 3.11
Classifier: Programming Language :: Python :: 3.12
Classifier: Programming Language :: Python :: 3.13
Classifier: Topic :: Software Development :: Libraries
Requires-Python: >=3.12
License-File: LICENSE
Requires-Dist: array-api-compat>=1.11.2
Requires-Dist: array-api-extra>=0.1.1
Requires-Dist: array-api-negative-index>=1.0.0
Requires-Dist: numba>=0.60.0
Requires-Dist: scipy>=1.13.1
Requires-Dist: types-array-api>=1.1.5
Provides-Extra: cli
Requires-Dist: rich>=10; extra == "cli"
Requires-Dist: typer<1,>=0.15; extra == "cli"
Requires-Dist: torch>=2.7.1; extra == "cli"
Requires-Dist: aquarel>=0.0.7; extra == "cli"
Requires-Dist: cm-time>=0.1.2; extra == "cli"
Requires-Dist: pandas>=2.3.1; extra == "cli"
Requires-Dist: seaborn>=0.13.2; extra == "cli"
Provides-Extra: cuda
Requires-Dist: numba-cuda>=0.19.1; extra == "cuda"
Dynamic: license-file
